<?xml version="1.0" encoding="utf-8"?>
<info>
    <career>
        <id>1</id>
        <name>Knight</name>
        <modelName>PlayerKnight</modelName>
        <health>100</health>
        <skills>
            <skill>
                <id>1001</id>
                <name>Attack 01</name>
                <damage>10</damage>
            </skill>
            <skill>
                <id>1002</id>
                <name>Attack 02</name>
                <damage>15</damage>
            </skill>
            <skill>
                <id>1003</id>
                <name>Double Attack</name>
                <damage>20</damage>
            </skill>
            <skill>
                <id>1004</id>
                <name>Cast Spell</name>
                <damage>30</damage>
            </skill>
        </skills>
    </career>
    <career>
        <id>2</id>
        <name>Wizard</name>
        <modelName>PlayerWizard</modelName>
        <health>100</health>
        <skills>
            <skill>
                <id>2001</id>
                <name>Melee Attack</name>
                <damage>10</damage>
            </skill>
            <skill>
                <id>2002</id>
                <name>Projectile Attack</name>
                <damage>15</damage>
            </skill>
            <skill>
                <id>2003</id>
                <name>Cast Spell 02</name>
                <damage>20</damage>
            </skill>
            <skill>
                <id>2004</id>
                <name>Channeling</name>
                <damage>25</damage>
            </skill>
            <skill>
                <id>2005</id>
                <name>Shockwave Attack</name>
                <damage>30</damage>
            </skill>
        </skills>
    </career>
</info>